setup.cfg
setup.py
chain_joiner/__init__.py
chain_joiner/chain_joiner.py
chain_joiner/make_alignment.py
chain_joiner/make_model.py
chain_joiner/make_seq.py
chain_joiner/run_chain_joiner_online.py
chain_joiner.egg-info/PKG-INFO
chain_joiner.egg-info/SOURCES.txt
chain_joiner.egg-info/dependency_links.txt
chain_joiner.egg-info/entry_points.txt
chain_joiner.egg-info/requires.txt
chain_joiner.egg-info/top_level.txt