Metadata-Version: 1.1
Name: chain-joiner
Version: 0.11
Summary: A package to automatically fix chain breaks in PDB files using MODELLER
Home-page: https://github.com/mc-robinson/chain_joiner
Author: Matthew C. Robinson
Author-email: matthew.robinson@yale.edu
License: UNKNOWN
Platform: UNKNOWN
Classifier: Programming Language :: Python :: 3.6
Classifier: Topic :: Scientific/Engineering
